{
    "agent": {
        "0": [
            10.88813082701832,
            0.1,
            1.191573999323606
        ],
        "1": [
            16.192780246873873,
            0.1,
            -0.6467304266731921
        ]
    },
    "avatar": {
        "id": "teaser",
        "position": {
            "x": 27,
            "y": 5,
            "z": 0.7
        },
        "look_at": {
            "x": 0,
            "y": 0,
            "z": 0.7
        }
    },
    "mass_map": {
        "9133855": 10,
        "14843021": 10,
        "13858235": 10,
        "7683376": 10,
        "8188729": 10,
        "6072145": 10,
        "3559329": 10,
        "6421134": 10,
        "1418342": 10,
        "5144974": 10,
        "14070343": 10,
        "13755059": 10,
        "2577501": 10,
        "10940621": 10,
        "9181080": 10,
        "6337927": 10,
        "11399518": 10,
        "645557": 10,
        "1082129": 10,
        "1781538": 10,
        "8164999": 10,
        "10032311": 10,
        "10298395": 10,
        "7122806": 10,
        "4589407": 10,
        "16165869": 10,
        "13926025": 10,
        "5854603": 10,
        "9726159": 10,
        "5266415": 10,
        "10361087": 10,
        "15115381": 10,
        "6383113": 10,
        "7514342": 10,
        "9434027": 10,
        "12452796": 10
    },
    "scene_id": 0,
    "task": {
        "goal_position_names": "fire hydrant",
        "goal_task": [
            [
                "apple",
                3
            ],
            [
                "b04_orange_00",
                3
            ],
            [
                "b04_red_grapes",
                3
            ],
            [
                "b03_banan_001",
                3
            ],
            [
                "b03_loafbread",
                3
            ]
        ],
        "container_names": [
            "basket_18inx18inx12iin_wicker",
            "basket_18inx18inx12iin_bamboo",
            "basket_18inx18inx12iin_wood_mesh"
        ],
        "task_kind": "outdoor_shopping",
        "constraint_type": "riding"
    },
    "bike_id": 11265357
}